ajsonrpc/__init__.py
ajsonrpc/core.py
ajsonrpc/dispatcher.py
ajsonrpc/manager.py
ajsonrpc/utils.py
ajsonrpc/backend/__init__.py
ajsonrpc/backend/common.py
ajsonrpc/backend/quart.py
ajsonrpc/backend/sanic.py
ajsonrpc/backend/tornado.py
ajsonrpc/scripts/server.py
ajsonrpc/tests/__init__.py
ajsonrpc/tests/test_core.py
ajsonrpc/tests/test_dispatcher.py
ajsonrpc/tests/test_manager.py
ajsonrpc-1.2.0.dist-info/LICENSE.txt
ajsonrpc-1.2.0.dist-info/METADATA
ajsonrpc-1.2.0.dist-info/WHEEL
ajsonrpc-1.2.0.dist-info/entry_points.txt
ajsonrpc-1.2.0.dist-info/top_level.txt
ajsonrpc-1.2.0.dist-info/RECORD
