Metadata-Version: 2.1
Name: ajsonrpc
Version: 1.2.0
Summary: Async JSON-RPC 2.0 protocol + server powered by asyncio
Home-page: https://github.com/pavlov99/ajsonrpc
Author: Kirill Pavlov
Author-email: k@p99.io
License: MIT
Project-URL: Documentation, https://ajsonrpc.readthedocs.io
Project-URL: Code, https://github.com/pavlov99/ajsonrpc
Project-URL: Issue tracker, https://github.com/pavlov99/ajsonrpc/issues
Platform: any
Classifier: Development Status :: 5 - Production/Stable
Classifier: Environment :: Console
Classifier: Framework :: AsyncIO
Classifier: Intended Audience :: Developers
Classifier: License :: OSI Approved :: MIT License
Classifier: Natural Language :: English
Classifier: Operating System :: OS Independent
Classifier: Programming Language :: Python :: 3
Classifier: Programming Language :: Python :: 3.5
Classifier: Programming Language :: Python :: 3.6
Classifier: Programming Language :: Python :: 3.7
Classifier: Programming Language :: Python :: 3.8
Classifier: Programming Language :: Python :: 3.9
Classifier: Topic :: Software Development :: Libraries :: Python Modules
Requires-Python: >=3.5
